README.md
setup.py
RsaIt.egg-info/PKG-INFO
RsaIt.egg-info/SOURCES.txt
RsaIt.egg-info/dependency_links.txt
RsaIt.egg-info/requires.txt
RsaIt.egg-info/top_level.txt
rsa_confirm/__init__.py
rsa_confirm/_core.py