Metadata-Version: 2.1
Name: RsaIt
Version: 0.0.3
Summary: upload pypi test-RsaConfirm
Home-page: https://github.com/LottoDog/rsa_confirm.git
Author: xiaobo666
Author-email: knightforiu@163.com
License: Apache 2.0
Keywords: RsaConfirm
Platform: UNKNOWN
Classifier: Development Status :: 3 - Alpha
Classifier: Intended Audience :: Developers
Classifier: Programming Language :: Python :: 3
Classifier: Programming Language :: Python :: 3.7
Classifier: Programming Language :: Python :: 3.8
Classifier: Programming Language :: Python :: 3.9
Classifier: Programming Language :: Python :: 3.10
Classifier: Programming Language :: Python :: 3 :: Only
Classifier: License :: OSI Approved :: MIT License
Classifier: Operating System :: OS Independent
